[
  {
    "file": "2026-03-23-us-open.md",
    "htmlFile": "2026-03-23-us-open.html",
    "title": "US Open +15m",
    "summary": "US Open +15m shows risk-on conditions. S&P +1.68%, NDQ +1.71%, 88% of tracked names positive, led by TSLA, BABA, AMZN.",
    "date": "2026-03-23",
    "slot": "us-open",
    "tickers": [
      "BTC-USD",
      "GC=F",
      "^GSPC",
      "^NDQ",
      "AAPL",
      "TSLA",
      "GOOG",
      "NVDA",
      "AMZN",
      "MSFT",
      "META",
      "DUOL",
      "ADBE.VI",
      "AMD",
      "BABA",
      "LMT",
      "BA",
      "TM",
      "MA",
      "NFLX",
      "RDDT",
      "NOVO-B.CO"
    ],
    "regime": "risk-on",
    "sections": {
      "gamma": [
        "Ticker | Price | Δ%",
        "---|---:|---:",
        "BTC-USD | 70721.31 | +4.24%",
        "GC=F | 4446.50 | +0.00%",
        "^GSPC | 6615.76 | +1.68%"
      ],
      "alpha": [
        "- The tape is clearly constructive: indices firm (S&P +1.68%, NDQ +1.71%) with 88% of tracked names positive — broad participation supports the move.",
        "- Rotation signals: defense bid (avg +1.11%); tech leading (avg +1.55%); payments holding (avg +1.44%); international strength.",
        "- Maintain full strategic exposure; add on pullbacks to liquid leaders with confirmed momentum."
      ],
      "beta": [
        "- Top movers: **TSLA (+3.50%)**, **BABA (+3.12%)**, **AMZN (+3.04%)**. No extreme outliers — moves reflect broad tape direction rather than isolated catalysts.",
        "- S&P holding +1.68% into open — allow incremental adds in confirmed leaders, but wait for 30-min opening range before sizing up.",
        "- Manage size on laggards: **LMT (-0.27%)**, **ADBE.VI (-0.19%)**, **RDDT (+0.06%)** are showing weakness — cut or hedge rather than averaging down against the tape."
      ],
      "pulse": [
        "Awaiting pulse update."
      ]
    },
    "movers": [
      {
        "ticker": "BTC-USD",
        "name": "BTC-USD",
        "price": "70721.31",
        "pct": 4.24,
        "change": "+2876.62",
        "changeValue": 2876.615065234073
      },
      {
        "ticker": "GC=F",
        "name": "GC=F",
        "price": "4446.50",
        "pct": 0,
        "change": "+0.00",
        "changeValue": 0
      },
      {
        "ticker": "^GSPC",
        "name": "^GSPC",
        "price": "6615.76",
        "pct": 1.68,
        "change": "+109.31",
        "changeValue": 109.30838709677391
      },
      {
        "ticker": "^NDQ",
        "name": "^NDQ",
        "price": "24307.51",
        "pct": 1.71,
        "change": "+408.67",
        "changeValue": 408.67016124274596
      },
      {
        "ticker": "AAPL",
        "name": "AAPL",
        "price": "252.72",
        "pct": 1.91,
        "change": "+4.74",
        "changeValue": 4.736485133941699
      },
      {
        "ticker": "TSLA",
        "name": "TSLA",
        "price": "380.82",
        "pct": 3.5,
        "change": "+12.88",
        "changeValue": 12.877971014492744
      },
      {
        "ticker": "GOOG",
        "name": "GOOG",
        "price": "300.40",
        "pct": 0.54,
        "change": "+1.61",
        "changeValue": 1.6134473841257204
      },
      {
        "ticker": "NVDA",
        "name": "NVDA",
        "price": "176.65",
        "pct": 2.29,
        "change": "+3.95",
        "changeValue": 3.9547218691954242
      },
      {
        "ticker": "AMZN",
        "name": "AMZN",
        "price": "211.61",
        "pct": 3.04,
        "change": "+6.24",
        "changeValue": 6.243152173913046
      },
      {
        "ticker": "MSFT",
        "name": "MSFT",
        "price": "384.71",
        "pct": 0.74,
        "change": "+2.83",
        "changeValue": 2.825942028985537
      },
      {
        "ticker": "META",
        "name": "META",
        "price": "607.47",
        "pct": 2.33,
        "change": "+13.83",
        "changeValue": 13.83177074171806
      },
      {
        "ticker": "DUOL",
        "name": "DUOL",
        "price": "98.69",
        "pct": 0.65,
        "change": "+0.64",
        "changeValue": 0.6373422752111253
      },
      {
        "ticker": "ADBE.VI",
        "name": "ADBE.VI",
        "price": "247.69",
        "pct": -0.19,
        "change": "-0.47",
        "changeValue": -0.4715068630397923
      },
      {
        "ticker": "AMD",
        "name": "AMD",
        "price": "204.89",
        "pct": 1.77,
        "change": "+3.56",
        "changeValue": 3.5634794143657302
      },
      {
        "ticker": "BABA",
        "name": "BABA",
        "price": "126.23",
        "pct": 3.12,
        "change": "+3.82",
        "changeValue": 3.8192164468580216
      },
      {
        "ticker": "LMT",
        "name": "LMT",
        "price": "625.74",
        "pct": -0.27,
        "change": "-1.69",
        "changeValue": -1.694071994384899
      },
      {
        "ticker": "BA",
        "name": "BA",
        "price": "199.98",
        "pct": 2.49,
        "change": "+4.86",
        "changeValue": 4.85852473412038
      },
      {
        "ticker": "TM",
        "name": "TM",
        "price": "210.70",
        "pct": 2.77,
        "change": "+5.68",
        "changeValue": 5.6790794979079635
      },
      {
        "ticker": "MA",
        "name": "MA",
        "price": "503.47",
        "pct": 1.44,
        "change": "+7.15",
        "changeValue": 7.147050473186084
      },
      {
        "ticker": "NFLX",
        "name": "NFLX",
        "price": "93.15",
        "pct": 1.45,
        "change": "+1.33",
        "changeValue": 1.3313701330704788
      },
      {
        "ticker": "RDDT",
        "name": "RDDT",
        "price": "139.94",
        "pct": 0.06,
        "change": "+0.08",
        "changeValue": 0.0839136518088992
      },
      {
        "ticker": "NOVO-B.CO",
        "name": "NOVO-B.CO",
        "price": "36.76",
        "pct": 0.64,
        "change": "+0.23",
        "changeValue": 0.2337678855325933
      }
    ]
  },
  {
    "file": "2026-03-23-pre-close.md",
    "htmlFile": "2026-03-23-pre-close.html",
    "title": "US Pre-close",
    "summary": "US Pre-close shows risk-on conditions. S&P +1.15%, NDQ +1.22%, 89% of tracked names positive, led by TSLA, BABA, TM.",
    "date": "2026-03-23",
    "slot": "pre-close",
    "tickers": [
      "BTC-USD",
      "GC=F",
      "^GSPC",
      "^NDQ",
      "AAPL",
      "TSLA",
      "GOOG",
      "NVDA",
      "AMZN",
      "MSFT",
      "META",
      "DUOL",
      "ADBE.VI",
      "AMD",
      "BABA",
      "LMT",
      "BA",
      "TM",
      "V",
      "MA",
      "NFLX",
      "RDDT",
      "NOVO-B.CO"
    ],
    "regime": "risk-on",
    "sections": {
      "gamma": [
        "Ticker | Price | Δ%",
        "---|---:|---:",
        "BTC-USD | 70928.05 | +4.54%",
        "GC=F | 4405.60 | +0.00%",
        "^GSPC | 6581.00 | +1.15%"
      ],
      "alpha": [
        "- The tape is clearly constructive: indices firm (S&P +1.15%, NDQ +1.22%) with 89% of tracked names positive — broad participation supports the move.",
        "- Rotation signals: tech leading (avg +1.00%); payments holding (avg +0.88%); international strength.",
        "- Maintain full strategic exposure; add on pullbacks to liquid leaders with confirmed momentum."
      ],
      "beta": [
        "- Top movers: **TSLA (+3.50%)**, **BABA (+2.98%)**, **TM (+2.74%)**. No extreme outliers — moves reflect broad tape direction rather than isolated catalysts.",
        "- Indices positive into the close — momentum names can be held or lightly added, but avoid chasing late-day rips.",
        "- Manage size on laggards: **LMT (-1.78%)**, **ADBE.VI (-0.21%)**, **GOOG (+0.08%)** are showing weakness — cut or hedge rather than averaging down against the tape."
      ],
      "pulse": [
        "Awaiting pulse update."
      ]
    },
    "movers": [
      {
        "ticker": "BTC-USD",
        "name": "BTC-USD",
        "price": "70928.05",
        "pct": 4.54,
        "change": "+3080.29",
        "changeValue": 3080.2883776544913
      },
      {
        "ticker": "GC=F",
        "name": "GC=F",
        "price": "4405.60",
        "pct": 0,
        "change": "+0.00",
        "changeValue": 0
      },
      {
        "ticker": "^GSPC",
        "name": "^GSPC",
        "price": "6581.00",
        "pct": 1.15,
        "change": "+74.82",
        "changeValue": 74.82105783489897
      },
      {
        "ticker": "^NDQ",
        "name": "^NDQ",
        "price": "24188.59",
        "pct": 1.22,
        "change": "+291.54",
        "changeValue": 291.5439616676558
      },
      {
        "ticker": "AAPL",
        "name": "AAPL",
        "price": "251.49",
        "pct": 1.41,
        "change": "+3.50",
        "changeValue": 3.496705453111133
      },
      {
        "ticker": "TSLA",
        "name": "TSLA",
        "price": "380.85",
        "pct": 3.5,
        "change": "+12.88",
        "changeValue": 12.878985507246341
      },
      {
        "ticker": "GOOG",
        "name": "GOOG",
        "price": "299.02",
        "pct": 0.08,
        "change": "+0.24",
        "changeValue": 0.23902478017583917
      },
      {
        "ticker": "NVDA",
        "name": "NVDA",
        "price": "175.64",
        "pct": 1.7,
        "change": "+2.94",
        "changeValue": 2.9359685349065785
      },
      {
        "ticker": "AMZN",
        "name": "AMZN",
        "price": "210.14",
        "pct": 2.32,
        "change": "+4.76",
        "changeValue": 4.764706802189238
      },
      {
        "ticker": "MSFT",
        "name": "MSFT",
        "price": "383.00",
        "pct": 0.3,
        "change": "+1.15",
        "changeValue": 1.1455633100697469
      },
      {
        "ticker": "META",
        "name": "META",
        "price": "604.06",
        "pct": 1.75,
        "change": "+10.39",
        "changeValue": 10.389238329238424
      },
      {
        "ticker": "DUOL",
        "name": "DUOL",
        "price": "99.75",
        "pct": 1.73,
        "change": "+1.70",
        "changeValue": 1.6963285166617652
      },
      {
        "ticker": "ADBE.VI",
        "name": "ADBE.VI",
        "price": "247.64",
        "pct": -0.21,
        "change": "-0.52",
        "changeValue": -0.5211383906203082
      },
      {
        "ticker": "AMD",
        "name": "AMD",
        "price": "202.68",
        "pct": 0.67,
        "change": "+1.35",
        "changeValue": 1.34891824774013
      },
      {
        "ticker": "BABA",
        "name": "BABA",
        "price": "126.06",
        "pct": 2.98,
        "change": "+3.65",
        "changeValue": 3.6478811419693216
      },
      {
        "ticker": "LMT",
        "name": "LMT",
        "price": "616.25",
        "pct": -1.78,
        "change": "-11.17",
        "changeValue": -11.168041132152325
      },
      {
        "ticker": "BA",
        "name": "BA",
        "price": "198.41",
        "pct": 1.69,
        "change": "+3.30",
        "changeValue": 3.2974028911397113
      },
      {
        "ticker": "TM",
        "name": "TM",
        "price": "210.64",
        "pct": 2.74,
        "change": "+5.62",
        "changeValue": 5.617613393030979
      },
      {
        "ticker": "V",
        "name": "V",
        "price": "304.44",
        "pct": 0.93,
        "change": "+2.81",
        "changeValue": 2.8052036064599406
      },
      {
        "ticker": "MA",
        "name": "MA",
        "price": "500.38",
        "pct": 0.82,
        "change": "+4.07",
        "changeValue": 4.069744098393187
      },
      {
        "ticker": "NFLX",
        "name": "NFLX",
        "price": "93.38",
        "pct": 1.7,
        "change": "+1.56",
        "changeValue": 1.560924287118965
      },
      {
        "ticker": "RDDT",
        "name": "RDDT",
        "price": "140.96",
        "pct": 0.79,
        "change": "+1.10",
        "changeValue": 1.104855640440519
      },
      {
        "ticker": "NOVO-B.CO",
        "name": "NOVO-B.CO",
        "price": "36.82",
        "pct": 0.79,
        "change": "+0.29",
        "changeValue": 0.28859807520587566
      }
    ]
  },
  {
    "file": "2026-03-23-eu.md",
    "htmlFile": "2026-03-23-eu.html",
    "title": "EU/Nordic Morning",
    "summary": "EU/Nordic Morning shows risk-off conditions. S&P -1.51%, NDQ -1.88%, 26% of tracked names positive, led by RDDT, MA, ADBE.VI.",
    "date": "2026-03-23",
    "slot": "eu",
    "tickers": [
      "BTC-USD",
      "GC=F",
      "^GSPC",
      "^NDQ",
      "AAPL",
      "TSLA",
      "GOOG",
      "NVDA",
      "AMZN",
      "MSFT",
      "META",
      "DUOL",
      "ADBE.VI",
      "AMD",
      "BABA",
      "LMT",
      "BA",
      "TM",
      "V",
      "MA",
      "NFLX",
      "RDDT",
      "NOVO-B.CO"
    ],
    "regime": "risk-off",
    "sections": {
      "gamma": [
        "Ticker | Price | Δ%",
        "---|---:|---:",
        "BTC-USD | 68020.58 | +0.26%",
        "GC=F | 4301.20 | +0.00%",
        "^GSPC | 6506.48 | -1.51%"
      ],
      "alpha": [
        "- Clear risk-off session: indices under pressure (S&P -1.51%, NDQ -1.88%) with 14/19 tracked names negative — selling is broad, not isolated.",
        "- Rotation signals: tech under pressure (avg -1.56%); payments holding (avg +0.85%); international weakness.",
        "- Reduce gross exposure; prioritize capital preservation over catching bounces. Re-assess after a session of stabilization."
      ],
      "beta": [
        "- Top movers: **RDDT (+1.25%)**, **MA (+1.05%)**, **ADBE.VI (+0.88%)**. No extreme outliers — moves reflect broad tape direction rather than isolated catalysts.",
        "- EU open is soft. Avoid pre-market chasing; wait for London open confirmation before committing to direction.",
        "- Manage size on laggards: **TSLA (-3.24%)**, **NVDA (-3.15%)**, **BA (-3.01%)** are showing weakness — cut or hedge rather than averaging down against the tape."
      ],
      "pulse": [
        "Awaiting pulse update."
      ]
    },
    "movers": [
      {
        "ticker": "BTC-USD",
        "name": "BTC-USD",
        "price": "68020.58",
        "pct": 0.26,
        "change": "+176.39",
        "changeValue": 176.39488130858808
      },
      {
        "ticker": "GC=F",
        "name": "GC=F",
        "price": "4301.20",
        "pct": 0,
        "change": "+0.00",
        "changeValue": 0
      },
      {
        "ticker": "^GSPC",
        "name": "^GSPC",
        "price": "6506.48",
        "pct": -1.51,
        "change": "-99.75",
        "changeValue": -99.75413544522326
      },
      {
        "ticker": "^NDQ",
        "name": "^NDQ",
        "price": "23898.15",
        "pct": -1.88,
        "change": "-457.89",
        "changeValue": -457.89362005707517
      },
      {
        "ticker": "AAPL",
        "name": "AAPL",
        "price": "247.99",
        "pct": -0.39,
        "change": "-0.97",
        "changeValue": -0.9709476960144627
      },
      {
        "ticker": "TSLA",
        "name": "TSLA",
        "price": "367.96",
        "pct": -3.24,
        "change": "-12.32",
        "changeValue": -12.321107895824696
      },
      {
        "ticker": "GOOG",
        "name": "GOOG",
        "price": "298.79",
        "pct": -2.27,
        "change": "-6.94",
        "changeValue": -6.940072649135402
      },
      {
        "ticker": "NVDA",
        "name": "NVDA",
        "price": "172.93",
        "pct": -3.15,
        "change": "-5.62",
        "changeValue": -5.624465668559623
      },
      {
        "ticker": "AMZN",
        "name": "AMZN",
        "price": "205.37",
        "pct": -1.62,
        "change": "-3.38",
        "changeValue": -3.3817788168326786
      },
      {
        "ticker": "MSFT",
        "name": "MSFT",
        "price": "381.85",
        "pct": -1.84,
        "change": "-7.16",
        "changeValue": -7.1577424612876825
      },
      {
        "ticker": "META",
        "name": "META",
        "price": "593.66",
        "pct": -2.15,
        "change": "-13.04",
        "changeValue": -13.044138988247255
      },
      {
        "ticker": "DUOL",
        "name": "DUOL",
        "price": "98.05",
        "pct": -1.56,
        "change": "-1.55",
        "changeValue": -1.5538195855343275
      },
      {
        "ticker": "ADBE.VI",
        "name": "ADBE.VI",
        "price": "248.15",
        "pct": 0.88,
        "change": "+2.16",
        "changeValue": 2.1646708961141883
      },
      {
        "ticker": "AMD",
        "name": "AMD",
        "price": "201.33",
        "pct": -1.92,
        "change": "-3.94",
        "changeValue": -3.9412071778140216
      },
      {
        "ticker": "BABA",
        "name": "BABA",
        "price": "122.41",
        "pct": -1.99,
        "change": "-2.49",
        "changeValue": -2.4854188348127764
      },
      {
        "ticker": "LMT",
        "name": "LMT",
        "price": "627.43",
        "pct": -1.58,
        "change": "-10.07",
        "changeValue": -10.072540134119095
      },
      {
        "ticker": "BA",
        "name": "BA",
        "price": "195.12",
        "pct": -3.01,
        "change": "-6.06",
        "changeValue": -6.055378905041749
      },
      {
        "ticker": "TM",
        "name": "TM",
        "price": "205.02",
        "pct": -1.87,
        "change": "-3.91",
        "changeValue": -3.906933659431388
      },
      {
        "ticker": "V",
        "name": "V",
        "price": "301.62",
        "pct": 0.64,
        "change": "+1.92",
        "changeValue": 1.9180922098569226
      },
      {
        "ticker": "MA",
        "name": "MA",
        "price": "496.32",
        "pct": 1.05,
        "change": "+5.16",
        "changeValue": 5.157209302325555
      },
      {
        "ticker": "NFLX",
        "name": "NFLX",
        "price": "91.82",
        "pct": 0.09,
        "change": "+0.08",
        "changeValue": 0.0825636926765867
      },
      {
        "ticker": "RDDT",
        "name": "RDDT",
        "price": "139.85",
        "pct": 1.25,
        "change": "+1.73",
        "changeValue": 1.7265432098765245
      },
      {
        "ticker": "NOVO-B.CO",
        "name": "NOVO-B.CO",
        "price": "36.53",
        "pct": -1.48,
        "change": "-0.55",
        "changeValue": -0.5487657328461211
      }
    ]
  }
]